fmu/__init__.py
fmu/sumo/__init__.py
fmu/sumo/explorer/__init__.py
fmu/sumo/explorer/_version.py
fmu/sumo/explorer/cache.py
fmu/sumo/explorer/explorer.py
fmu/sumo/explorer/filters.py
fmu/sumo/explorer/timefilter.py
fmu/sumo/explorer/objects/__init__.py
fmu/sumo/explorer/objects/_child.py
fmu/sumo/explorer/objects/_document.py
fmu/sumo/explorer/objects/_metrics.py
fmu/sumo/explorer/objects/_search_context.py
fmu/sumo/explorer/objects/case.py
fmu/sumo/explorer/objects/cases.py
fmu/sumo/explorer/objects/cpgrid.py
fmu/sumo/explorer/objects/cpgrid_property.py
fmu/sumo/explorer/objects/cube.py
fmu/sumo/explorer/objects/dictionary.py
fmu/sumo/explorer/objects/ensemble.py
fmu/sumo/explorer/objects/ensembles.py
fmu/sumo/explorer/objects/polygons.py
fmu/sumo/explorer/objects/realization.py
fmu/sumo/explorer/objects/realizations.py
fmu/sumo/explorer/objects/surface.py
fmu/sumo/explorer/objects/table.py
fmu_sumo-2.9.0.dist-info/licenses/LICENSE
fmu_sumo-2.9.0.dist-info/METADATA
fmu_sumo-2.9.0.dist-info/WHEEL
fmu_sumo-2.9.0.dist-info/top_level.txt
fmu_sumo-2.9.0.dist-info/RECORD
