Metadata-Version: 2.4
Name: fmu-sumo
Version: 2.9.0
Summary: Python package for interacting with Sumo in an FMU setting
Author: Equinor
License:                                  Apache License
Project-URL: Repository, https://github.com/equinor/fmu-sumo
Platform: any
Classifier: License :: OSI Approved :: Apache Software License
Classifier: Programming Language :: Python
Requires-Python: >=3.11
License-File: LICENSE
Requires-Dist: sumo-wrapper-python
Requires-Dist: deprecation
Provides-Extra: all
Requires-Dist: xtgeo; extra == "all"
Requires-Dist: pandas>=1.1.3; extra == "all"
Requires-Dist: pyarrow; python_version > "3.6.1" and extra == "all"
Requires-Dist: OpenVDS; (sys_platform != "darwin" and python_version < "3.12") and extra == "all"
Provides-Extra: dev
Requires-Dist: ruff; extra == "dev"
Requires-Dist: pytest; extra == "dev"
Provides-Extra: test
Requires-Dist: xtgeo; extra == "test"
Requires-Dist: pandas>=1.1.3; extra == "test"
Requires-Dist: pyarrow; python_version > "3.6.1" and extra == "test"
Requires-Dist: OpenVDS; (sys_platform != "darwin" and python_version < "3.12") and extra == "test"
Requires-Dist: pytest; extra == "test"
Requires-Dist: pytest-timeout; extra == "test"
Provides-Extra: docs
Requires-Dist: sphinx==6.2.1; extra == "docs"
Requires-Dist: sphinx-rtd-theme; extra == "docs"
Requires-Dist: autoapi; extra == "docs"
Requires-Dist: sphinx-autodoc-typehints; extra == "docs"
Requires-Dist: sphinxcontrib-apidoc; extra == "docs"
Dynamic: license-file
